api_cli.py
setup-lib.py
cli/__init__.py
cli/allow_commands.py
cli/labelizer_template.py
cli/postprocessor_template.py
cli/preprocessor_template.py
ds_framework.egg-info/PKG-INFO
ds_framework.egg-info/SOURCES.txt
ds_framework.egg-info/dependency_links.txt
ds_framework.egg-info/entry_points.txt
ds_framework.egg-info/requires.txt
ds_framework.egg-info/top_level.txt
lib/__init__.py
lib/base_classes/__init__.py
lib/base_classes/attributes_extractor_base.py
lib/base_classes/forcer_base.py
lib/base_classes/object_base.py
lib/base_classes/predictable_base.py
lib/base_classes/predictor_base.py
lib/config/__init__.py
lib/config/zids_config.py
lib/pipeline/__init__.py
lib/pipeline/labelizer_base.py
lib/pipeline/pipeline_base.py
lib/pipeline/postprocess_base.py
lib/pipeline/preprocess_base.py
lib/shared/__init__.py
lib/shared/shared_objects.py
lib/utils/__init__.py
lib/utils/functions.py
lib/utils/regex_handler.py