Metadata-Version: 2.1
Name: ds-framework
Version: 0.1.1
Summary: My first Python library
Home-page: UNKNOWN
Author: oribrau@gmail.com
License: MIT
Platform: UNKNOWN
